{
  "title": "NASA’s Newest Wind Tunnel Builds on Legacy of Innovation",
  "source": "NASA",
  "link": "https://www.nasa.gov/centers-and-facilities/langley/nasas-newest-wind-tunnel-builds-on-legacy-of-innovation/",
  "score": 80,
  "summary": "NASA has built a new wind tunnel, the Flight Dynamics Research Facility (FDRF), that will be a key player in aeronautics research. This facility has more advanced capabilities than previous ones and will allow for more accurate simulations of real flight conditions.",
  "script": "새로운 풍속실이 설치되었습니다! 🎉\nNASA의 새로운 풍속실, FDRF는 최첨단 기술을 동반해 꿈과 여정을 향한 진행을 이끌어낼 것입니다!\n40년 이상 지나온 시간 동안 만들어진 풍력실의 역사를 살펴보세요.\n이제 더욱 정확하고 광범위한 연구가 가능합니다.",
  "thumbnail": "풍속실 & NASA",
  "hashtags": [
    "#공기역학",
    "#인공지능",
    "#우주탐험",
    "#프로그래밍",
    "#NASA"
  ],
  "created_at": "2026-07-01T22:14:54.233012"
}